Metadata-Version: 2.1
Name: i2db
Version: 1.0
Summary: My Online DB
Home-page: UNKNOWN
Author: Zaid Ali
Author-email: email@iexi.xyz
License: MIT
Keywords: db,database,json
Platform: UNKNOWN
Classifier: Development Status :: 1 - Planning
Classifier: Intended Audience :: Developers
Classifier: Programming Language :: Python :: 3
Classifier: Operating System :: Unix
Classifier: Operating System :: MacOS :: MacOS X
Classifier: Operating System :: Microsoft :: Windows
